Aspidites-1.16.1.dist-info/entry_points.txt
Aspidites-1.16.1.dist-info/top_level.txt
Aspidites-1.16.1.dist-info/WHEEL
Aspidites-1.16.1.dist-info/RECORD
Aspidites-1.16.1.dist-info/LICENSE
Aspidites-1.16.1.dist-info/METADATA
dev/__init__.py
Aspidites/math.c
Aspidites/__main__.c
Aspidites/compiler.cpython-39-x86_64-linux-gnu.so
Aspidites/compiler.c
Aspidites/monads.py
Aspidites/compiler.py
Aspidites/math.cpython-39-x86_64-linux-gnu.so
Aspidites/templates.py
Aspidites/__main__.cpython-39-x86_64-linux-gnu.so
Aspidites/api.py
Aspidites/templates.cpython-39-x86_64-linux-gnu.so
Aspidites/__init__.py
Aspidites/api.c
Aspidites/templates.c
Aspidites/api.cpython-39-x86_64-linux-gnu.so
Aspidites/final.py
Aspidites/monads.cpython-39-x86_64-linux-gnu.so
Aspidites/monads.c
Aspidites/repl.py
Aspidites/type_guard.py
Aspidites/math.py
Aspidites/__main__.py
Aspidites/_vendor/pyparsing.py
Aspidites/_vendor/decorator.py
Aspidites/_vendor/pyparsing_extension.c
Aspidites/_vendor/decorator_extension.c
Aspidites/_vendor/_compat.py
Aspidites/_vendor/decorator_extension.py
Aspidites/_vendor/__init__.py
Aspidites/_vendor/decorator_extension.cpython-39-x86_64-linux-gnu.so
Aspidites/_vendor/pyparsing_extension.py
Aspidites/_vendor/pyparsing_extension.cpython-39-x86_64-linux-gnu.so
Aspidites/_vendor/semantic_version.py
Aspidites/_vendor/pyparsing_unicode.py
Aspidites/_vendor/contracts/interface.cpython-39-x86_64-linux-gnu.so
Aspidites/_vendor/contracts/interface.py
Aspidites/_vendor/contracts/metaclass.cpython-39-x86_64-linux-gnu.so
Aspidites/_vendor/contracts/pyparsing_utils.py
Aspidites/_vendor/contracts/main.py
Aspidites/_vendor/contracts/inspection.c
Aspidites/_vendor/contracts/__init__.py
Aspidites/_vendor/contracts/metaclass.c
Aspidites/_vendor/contracts/docstring_parsing.cpython-39-x86_64-linux-gnu.so
Aspidites/_vendor/contracts/main_actual.c
Aspidites/_vendor/contracts/inspection.py
Aspidites/_vendor/contracts/test_registrar.py
Aspidites/_vendor/contracts/docstring_parsing.c
Aspidites/_vendor/contracts/interface.c
Aspidites/_vendor/contracts/main_actual.cpython-39-x86_64-linux-gnu.so
Aspidites/_vendor/contracts/docstring_parsing.py
