Metadata-Version: 2.1
Name: Aspidites
Version: 1.16.1
Summary: Aspidites is the reference implementation of the Woma Language
Home-page: https://github.com/rjdbcm/Aspidites
Author: Ross J. Duff
Author-email: rjdbcm@mail.umkc.edu
License: GPL
Keywords: language
Platform: UNKNOWN
Classifier: Operating System :: POSIX :: Linux
Classifier: Operating System :: MacOS :: MacOS X
Classifier: Operating System :: Microsoft :: Windows
Classifier: Development Status :: 4 - Beta
Classifier: Environment :: Console
Classifier: Programming Language :: Other
Classifier: Programming Language :: Python :: 3.7
Classifier: Programming Language :: Python :: 3.8
Classifier: Programming Language :: Python :: 3.9
Classifier: Programming Language :: Python :: Implementation :: CPython
Classifier: Topic :: Software Development :: Compilers
Classifier: Topic :: Utilities
Classifier: License :: OSI Approved :: GNU General Public License v3 or later (GPLv3+)
Classifier: License :: OSI Approved :: MIT License
Classifier: License :: OSI Approved :: BSD License
Classifier: License :: OSI Approved :: Apache Software License
License-File: LICENSE
